imas_mcp/__init__.py
imas_mcp/__main__.py
imas_mcp/cli.py
imas_mcp/dd_accessor.py
imas_mcp/graph_analyzer.py
imas_mcp/health.py
imas_mcp/physics_integration.py
imas_mcp/providers.py
imas_mcp/resource_path_accessor.py
imas_mcp/resource_provider.py
imas_mcp/search_result.py
imas_mcp/server.py
imas_mcp/core/__init__.py
imas_mcp/core/data_model.py
imas_mcp/core/domain_loader.py
imas_mcp/core/physics_accessors.py
imas_mcp/core/physics_categorization.py
imas_mcp/core/physics_context.py
imas_mcp/core/physics_domains.py
imas_mcp/core/progress_monitor.py
imas_mcp/core/relationships.py
imas_mcp/core/unit_loader.py
imas_mcp/core/xml_parser.py
imas_mcp/core/xml_utils.py
imas_mcp/core/extractors/__init__.py
imas_mcp/core/extractors/base.py
imas_mcp/core/extractors/coordinate_extractor.py
imas_mcp/core/extractors/identifier_extractor.py
imas_mcp/core/extractors/metadata_extractor.py
imas_mcp/core/extractors/physics_extractor.py
imas_mcp/core/extractors/relationship_extractor.py
imas_mcp/core/extractors/semantic_extractor.py
imas_mcp/core/extractors/validation_extractor.py
imas_mcp/definitions/README.md
imas_mcp/definitions/__init__.py
imas_mcp/definitions/imas/complexity_thresholds.yaml
imas_mcp/definitions/imas/hierarchy_patterns.yaml
imas_mcp/definitions/imas/navigation_templates.yaml
imas_mcp/definitions/imas/data_dictionary/.gitkeep
imas_mcp/definitions/imas/metadata/.gitkeep
imas_mcp/definitions/imas/workflows/.gitkeep
imas_mcp/definitions/physics/__init__.py
imas_mcp/definitions/physics/constants/.gitkeep
imas_mcp/definitions/physics/constants/fundamental.yaml
imas_mcp/definitions/physics/domains/characteristics.yaml
imas_mcp/definitions/physics/domains/diagnostic_methods.yaml
imas_mcp/definitions/physics/domains/ids_mapping.yaml
imas_mcp/definitions/physics/domains/measurement_types.yaml
imas_mcp/definitions/physics/domains/physics_contexts.yaml
imas_mcp/definitions/physics/domains/relationships.yaml
imas_mcp/definitions/physics/domains/research_workflows.yaml
imas_mcp-3.0.1.dist-info/METADATA
imas_mcp-3.0.1.dist-info/WHEEL
imas_mcp-3.0.1.dist-info/entry_points.txt
imas_mcp-3.0.1.dist-info/RECORD
