Metadata-Version: 2.4
Name: imas-mcp
Version: 3.0.1
Summary: An IMAS Data Dictionary MCP server
Project-URL: Homepage, https://github.com/iterorganization/imas-mcp
Project-URL: Repository, https://github.com/iterorganization/imas-mcp
Project-URL: Documentation, https://github.com/iterorganization/imas-mcp#readme
Project-URL: Bug Tracker, https://github.com/iterorganization/imas-mcp/issues
Author-email: Simon McIntosh <simon.mcintosh@iter.org>
License: CC BY-ND 4.0
Keywords: Data Dictionary,Fusion,IMAS,ITER,MCP,Model Context Protocol,Plasma Physics
Classifier: Development Status :: 4 - Beta
Classifier: Intended Audience :: Developers
Classifier: Intended Audience :: Science/Research
Classifier: License :: Other/Proprietary License
Classifier: Operating System :: OS Independent
Classifier: Programming Language :: Python :: 3
Classifier: Programming Language :: Python :: 3.12
Classifier: Topic :: Database :: Database Engines/Servers
Classifier: Topic :: Scientific/Engineering :: Physics
Classifier: Topic :: Software Development :: Libraries :: Python Modules
Requires-Python: <3.13,>=3.12
Requires-Dist: cachetools<6.0.0,>=5.3.0
Requires-Dist: click<9.0.0,>=8.0.0
Requires-Dist: fastapi<1.0.0,>=0.100.0
Requires-Dist: fastmcp>=2.12.0
Requires-Dist: huggingface-hub[hf-xet]>=0.33.4
Requires-Dist: imas-data-dictionaries>=4.0.0
Requires-Dist: nest-asyncio<2.0.0,>=1.5.0
Requires-Dist: networkx<4.0,>=3.0
Requires-Dist: numpy>=2.3.1
Requires-Dist: pint<0.25.0,>=0.24.4
Requires-Dist: pydantic<3.0.0,>=2.11.4
Requires-Dist: pyyaml<7.0,>=6.0
Requires-Dist: sentence-transformers>=5.0.0
Requires-Dist: starlette<1.0.0,>=0.37.0
Requires-Dist: uvicorn<1.0.0,>=0.30.0
Provides-Extra: bench
Requires-Dist: asv<1.0.0,>=0.6.0; extra == 'bench'
Provides-Extra: test
Requires-Dist: coverage>=7.0.0; extra == 'test'
Requires-Dist: pytest-asyncio<1.0.0,>=0.21.0; extra == 'test'
Requires-Dist: pytest-benchmark<5.0.0,>=4.0.0; extra == 'test'
Requires-Dist: pytest-cov<7.0.0,>=6.1.1; extra == 'test'
Requires-Dist: pytest-timeout<3.0.0,>=2.1.0; extra == 'test'
Requires-Dist: pytest-xdist<4.0.0,>=3.0.0; extra == 'test'
Requires-Dist: pytest<9.0.0,>=8.3.5; extra == 'test'
